beautify_markdown/__init__.py
beautify_markdown/beautify_markdown.py
beautify_markdown-1.0.1.dist-info/METADATA
beautify_markdown-1.0.1.dist-info/WHEEL
beautify_markdown-1.0.1.dist-info/entry_points.txt
beautify_markdown-1.0.1.dist-info/top_level.txt
beautify_markdown-1.0.1.dist-info/RECORD
