Metadata-Version: 2.1
Name: beautify_markdown
Version: 1.0.1
Summary: A tool to beautify markdown output from chatgpt-cli (https://github.com/marcolardera/chatgpt-cli)
Home-page: https://github.com/tadeasf/beautify_markdown
Author: Tadeas Fort
Author-email: taddy.fort@gmail.com
Classifier: Programming Language :: Python :: 3
Classifier: License :: OSI Approved :: MIT License
Classifier: Operating System :: OS Independent
Requires-Python: >=3.11
Requires-Dist: rich
Requires-Dist: pyperclip
